langchain_utcp_adapters-0.1.0.dist-info/METADATA
langchain_utcp_adapters-0.1.0.dist-info/WHEEL
langchain_utcp_adapters-0.1.0.dist-info/entry_points.txt
langchain_utcp_adapters-0.1.0.dist-info/licenses/LICENSE
langchain_utcp_adapters/__init__.py
langchain_utcp_adapters/bedrock_utils.py
langchain_utcp_adapters/tools.py
langchain_utcp_adapters-0.1.0.dist-info/RECORD
