Metadata-Version: 2.4
Name: langchain-utcp-adapters
Version: 0.1.0
Summary: Make Universal Tool Calling Protocol (UTCP) tools compatible with LangChain and LangGraph agents.
Author: UTCP Adapters Team
License-Expression: MIT
Requires-Python: >=3.10
Requires-Dist: langchain-core<0.4,>=0.3.36
Requires-Dist: utcp>=1.0.0
Requires-Dist: typing-extensions>=4.14.0
Requires-Dist: pydantic>=2.0
Requires-Dist: aiohttp>=3.8
